DirectGuiDesigner/DirectGuiDesigner.py
DirectGuiDesigner/__init__.py
DirectGuiDesigner/GUI/MainView.py
DirectGuiDesigner/GUI/__init__.py
DirectGuiDesigner/core/CustomWidgets.py
DirectGuiDesigner/core/ElementHandler.py
DirectGuiDesigner/core/ElementInfo.py
DirectGuiDesigner/core/KillRing.py
DirectGuiDesigner/core/PropertyHelper.py
DirectGuiDesigner/core/WidgetDefinition.py
DirectGuiDesigner/core/__init__.py
DirectGuiDesigner/dialogs/PathSelect.py
DirectGuiDesigner/dialogs/SettingsDialog.py
DirectGuiDesigner/dialogs/__init__.py
DirectGuiDesigner/directGuiOverrides/DirectEntryScroll.py
DirectGuiDesigner/directGuiOverrides/DirectOptionMenu.py
DirectGuiDesigner/directGuiOverrides/DirectScrollBar.py
DirectGuiDesigner/directGuiOverrides/DirectScrolledFrame.py
DirectGuiDesigner/directGuiOverrides/DirectSlider.py
DirectGuiDesigner/directGuiOverrides/__init__.py
DirectGuiDesigner/export/ExporterProject.py
DirectGuiDesigner/export/ExporterPy.py
DirectGuiDesigner/export/__init__.py
DirectGuiDesigner/fonts/DejaVuSansMono-Bold.ttf
DirectGuiDesigner/icons/ArrowDownSmall.png
DirectGuiDesigner/icons/ArrowUpSmall.png
DirectGuiDesigner/icons/Collapse.png
DirectGuiDesigner/icons/Collapsed.png
DirectGuiDesigner/icons/CycleRedo.png
DirectGuiDesigner/icons/Delete.png
DirectGuiDesigner/icons/DeleteSmall.png
DirectGuiDesigner/icons/DirectGuiDesigner128.png
DirectGuiDesigner/icons/DirectGuiDesigner16.png
DirectGuiDesigner/icons/DirectGuiDesigner192.png
DirectGuiDesigner/icons/DirectGuiDesigner256.png
DirectGuiDesigner/icons/DirectGuiDesigner32.png
DirectGuiDesigner/icons/DirectGuiDesigner64.png
DirectGuiDesigner/icons/Export.png
DirectGuiDesigner/icons/GridOff.png
DirectGuiDesigner/icons/GridOn.png
DirectGuiDesigner/icons/Help.png
DirectGuiDesigner/icons/Load.png
DirectGuiDesigner/icons/New.png
DirectGuiDesigner/icons/Quit.png
DirectGuiDesigner/icons/Redo.png
DirectGuiDesigner/icons/Reload.png
DirectGuiDesigner/icons/Save.png
DirectGuiDesigner/icons/Scale1.png
DirectGuiDesigner-22.4.1.dist-info/LICENSE
DirectGuiDesigner-22.4.1.dist-info/METADATA
DirectGuiDesigner-22.4.1.dist-info/WHEEL
DirectGuiDesigner-22.4.1.dist-info/top_level.txt
DirectGuiDesigner-22.4.1.dist-info/RECORD
