Metadata-Version: 2.1
Name: DirectGuiDesigner
Version: 22.4.1
Summary: An editor for the Panda3D engines DirectGUI UI framework
Home-page: https://github.com/fireclawthefox/DirectGuiDesigner
Author: Fireclaw
Author-email: fireclawthefox@gmail.com
License: UNKNOWN
Platform: UNKNOWN
Classifier: Programming Language :: Python :: 3
Classifier: License :: OSI Approved :: BSD License
Classifier: Operating System :: OS Independent
Classifier: Development Status :: 4 - Beta
Classifier: Intended Audience :: Developers
Classifier: Intended Audience :: End Users/Desktop
Classifier: Topic :: Artistic Software
Classifier: Topic :: Multimedia :: Graphics
Classifier: Topic :: Multimedia :: Graphics :: Editors
Requires-Python: >=3.6
License-File: LICENSE
Requires-Dist: panda3d
Requires-Dist: DirectFolderBrowser
Requires-Dist: DirectGuiExtension
